messari/__init__.py
messari/__version__.py
messari/messari.py
messari-2.1.0.dist-info/LICENSE
messari-2.1.0.dist-info/METADATA
messari-2.1.0.dist-info/WHEEL
messari-2.1.0.dist-info/top_level.txt
messari-2.1.0.dist-info/RECORD
